visorRobot/__init__.py
visorRobot/visor.py
visorRobot_test_02-0.0.1.dist-info/METADATA
visorRobot_test_02-0.0.1.dist-info/WHEEL
visorRobot_test_02-0.0.1.dist-info/top_level.txt
visorRobot_test_02-0.0.1.dist-info/RECORD
